{"cases":[{"country":"Afghanistan","cases":"233","iso":"AFG"},{"country":"Africa","cases":"31,983","iso":"Africa"},{"country":"Albania","cases":["Jan 28, 2022","1,549"],"iso":"ALB"},{"country":"Algeria","cases":"1,742","iso":"DZA"},{"country":"Andorra","cases":["Jan 28, 2022","528"],"iso":"AND"},{"country":"Angola","cases":"28","iso":"AGO"},{"country":"Anguilla","cases":"0","iso":"Anguilla"},{"country":"Antigua and Barbuda","cases":"0","iso":"ATG"},{"country":"Argentina","cases":"41,978","iso":"ARG"},{"country":"Armenia","cases":"2,594","iso":"ARM"},{"country":"Aruba","cases":"92","iso":"ABW"},{"country":"Asia","cases":"658,166","iso":"Asia"},{"country":"Australia","cases":"47,258","iso":"AUS"},{"country":"Austria","cases":"34,748","iso":"AUT"},{"country":"Azerbaijan","cases":"4,268","iso":"AZE"},{"country":"Bahamas","cases":"67","iso":"BHS"},{"country":"Bahrain","cases":"6,708","iso":"BHR"},{"country":"Bangladesh","cases":"10,378","iso":"BGD"},{"country":"Barbados","cases":"630","iso":"BRB"},{"country":"Belarus","cases":"2,302","iso":"BLR"},{"country":"Belgium","cases":["Jan 28, 2022","48,201"],"iso":"BEL"},{"country":"Belize","cases":["Jan 28, 2022","693"],"iso":"BLZ"},{"country":"Benin","cases":["Jan 26, 2022","141"],"iso":"BEN"},{"country":"Bermuda","cases":["Jan 27, 2022","290"],"iso":"Bermuda"},{"country":"Bhutan","cases":"136","iso":"BTN"},{"country":"Bolivia","cases":"5,423","iso":"BOL"},{"country":"Bonaire Sint Eustatius and Saba","cases":"46","iso":"Bonaire_Sint_Eustatius_and_Saba"},{"country":"Bosnia and Herzegovina","cases":["Jan 28, 2022","2,073"],"iso":"BIH"},{"country":"Botswana","cases":["Jan 27, 2022","4,842"],"iso":"BWA"},{"country":"Brazil","cases":"205,597","iso":"BRA"},{"country":"British Virgin Islands","cases":"0","iso":"British_Virgin_Islands"},{"country":"Brunei","cases":"52","iso":"BRN"},{"country":"Bulgaria","cases":"5,875","iso":"BGR"},{"country":"Burkina Faso","cases":"0","iso":"BFA"},{"country":"Burundi","cases":"0","iso":"BDI"},{"country":"Cambodia","cases":"54","iso":"KHM"},{"country":"Cameroon","cases":"0","iso":"CMR"},{"country":"Canada","cases":"9,867","iso":"CAN"},{"country":"Cape Verde","cases":"23","iso":"Cape_Verde"},{"country":"Cayman Islands","cases":"0","iso":"CYM"},{"country":"Central African Republic","cases":"0","iso":"CAF"},{"country":"Chad","cases":"0","iso":"TCD"},{"country":"Chile","cases":"31,909","iso":"CHL"},{"country":"China","cases":"81","iso":"CHN"},{"country":"Colombia","cases":"18,450","iso":"COL"},{"country":"Comoros","cases":"2","iso":"COM"},{"country":"Congo","cases":["Jan 27, 2022","168"],"iso":"COD"},{"country":"Cook Islands","cases":"0","iso":"Cook_Islands"},{"country":"Costa Rica","cases":["Jan 28, 2022","7,302"],"iso":"CRI"},{"country":"Cote d'Ivoire","cases":"57","iso":"CIV"},{"country":"Croatia","cases":"9,904","iso":"HRV"},{"country":"Cuba","cases":"3,059","iso":"CUB"},{"country":"Curacao","cases":"92","iso":"CUW"},{"country":"Cyprus","cases":"2,184","iso":"CYP"},{"country":"Czechia","cases":"47,427","iso":"CZE"},{"country":"Democratic Republic of Congo","cases":"0","iso":"Democratic_Republic_of_Congo"},{"country":"Denmark","cases":"41,083","iso":"DNK"},{"country":"Djibouti","cases":"11","iso":"DJI"},{"country":"Dominica","cases":"194","iso":"DMA"},{"country":"Dominican Republic","cases":"1,303","iso":"DOM"},{"country":"Ecuador","cases":["Jan 26, 2022","33,853"],"iso":"ECU"},{"country":"Egypt","cases":"2,018","iso":"EGY"},{"country":"El Salvador","cases":"6,250","iso":"SLV"},{"country":"Equatorial Guinea","cases":"0","iso":"GNQ"},{"country":"Eritrea","cases":"19","iso":"ERI"},{"country":"Estonia","cases":"7,124","iso":"EST"},{"country":"Eswatini","cases":"28","iso":"SWZ"},{"country":"Ethiopia","cases":"371","iso":"ETH"},{"country":"Europe","cases":"1.25 million","iso":"Europe"},{"country":"European Union","cases":"986,819","iso":"European_Union"},{"country":"Faeroe Islands","cases":"1,210","iso":"Faeroe_Islands"},{"country":"Falkland Islands","cases":"0","iso":"Falkland_Islands"},{"country":"Fiji","cases":["Jan 28, 2022","170"],"iso":"FJI"},{"country":"Finland","cases":["Jan 28, 2022","4,766"],"iso":"FIN"},{"country":"France","cases":"332,398","iso":"FRA"},{"country":"French Polynesia","cases":["Jan 27, 2022","250"],"iso":"French_Polynesia"},{"country":"Gabon","cases":["Jan 28, 2022","253"],"iso":"GAB"},{"country":"Gambia","cases":"270","iso":"GMB"},{"country":"Georgia","cases":"18,274","iso":"GEO"},{"country":"Germany","cases":"113,190","iso":"DEU"},{"country":"Ghana","cases":"175","iso":"GHA"},{"country":"Gibraltar","cases":"142","iso":"GIB"},{"country":"Greece","cases":"19,584","iso":"GRC"},{"country":"Greenland","cases":"94","iso":"GRL"},{"country":"Grenada","cases":"65","iso":"GRD"},{"country":"Guatemala","cases":"2,784","iso":"GTM"},{"country":"Guinea","cases":"0","iso":"GIN"},{"country":"Guinea-Bissau","cases":"32","iso":"GNB"},{"country":"Guyana","cases":"846","iso":"GUY"},{"country":"Haiti","cases":["Jan 27, 2022","314"],"iso":"HTI"},{"country":"High income","cases":"1.49 million","iso":"High_income"},{"country":"Honduras","cases":["Jan 27, 2022","729"],"iso":"HND"},{"country":"Hong Kong","cases":"80","iso":"Hong_Kong"},{"country":"Hungary","cases":["Jan 28, 2022","17,869"],"iso":"HUN"},{"country":"Iceland","cases":["Jan 28, 2022","1,298"],"iso":"ISL"},{"country":"India","cases":"234,281","iso":"IND"},{"country":"Indonesia","cases":"11,588","iso":"IDN"},{"country":"International","cases":"0","iso":"International"},{"country":"Iran","cases":"11,731","iso":"IRN"},{"country":"Iraq","cases":"5,827","iso":"IRQ"},{"country":"Ireland","cases":["Jan 28, 2022","5,109"],"iso":"IRL"},{"country":"Isle of Man","cases":"84","iso":"Isle_of_Man"},{"country":"Israel","cases":"53,928","iso":"ISR"},{"country":"Italy","cases":"137,427","iso":"ITA"},{"country":"Jamaica","cases":["Jan 28, 2022","584"],"iso":"JAM"},{"country":"Japan","cases":"84,795","iso":"JPN"},{"country":"Jordan","cases":"8,170","iso":"JOR"},{"country":"Kazakhstan","cases":"9,792","iso":"KAZ"},{"country":"Kenya","cases":"123","iso":"KEN"},{"country":"Kiribati","cases":"65","iso":"KIR"},{"country":"Kosovo","cases":"3,628","iso":"RKS"},{"country":"Kuwait","cases":"5,808","iso":"KWT"},{"country":"Kyrgyzstan","cases":["Jan 28, 2022","356"],"iso":"KGZ"},{"country":"Laos","cases":"537","iso":"LAO"},{"country":"Latvia","cases":"9,626","iso":"LVA"},{"country":"Lebanon","cases":"7,726","iso":"LBN"},{"country":"Lesotho","cases":["Jan 28, 2022","127"],"iso":"LSO"},{"country":"Liberia","cases":"0","iso":"LBR"},{"country":"Libya","cases":["Jan 28, 2022","3,320"],"iso":"LBY"},{"country":"Liechtenstein","cases":"185","iso":"LIE"},{"country":"Lithuania","cases":"12,517","iso":"LTU"},{"country":"Low income","cases":"3,345","iso":"Low_income"},{"country":"Lower middle income","cases":"392,022","iso":"Lower_middle_income"},{"country":"Luxembourg","cases":["Jan 28, 2022","2,552"],"iso":"LUX"},{"country":"Macao","cases":"0","iso":"Macao"},{"country":"Madagascar","cases":"1,944","iso":"MDG"},{"country":"Malawi","cases":"80","iso":"MWI"},{"country":"Malaysia","cases":"5,139","iso":"MYS"},{"country":"Maldives","cases":"2,689","iso":"MDV"},{"country":"Mali","cases":"25","iso":"MLI"},{"country":"Malta","cases":"190","iso":"MLT"},{"country":"Marshall Islands","cases":"0","iso":"MHL"},{"country":"Mauritania","cases":"88","iso":"MRT"},{"country":"Mauritius","cases":["Jan 28, 2022","105"],"iso":"MUS"},{"country":"Mexico","cases":"42,582","iso":"MEX"},{"country":"Micronesia (country)","cases":"0","iso":"Micronesia_(country)"},{"country":"Moldova","cases":"3,700","iso":"MDA"},{"country":"Monaco","cases":["Jan 28, 2022","393"],"iso":"MCO"},{"country":"Mongolia","cases":"1,834","iso":"MNG"},{"country":"Montenegro","cases":"885","iso":"MNE"},{"country":"Montserrat","cases":"1","iso":"Montserrat"},{"country":"Morocco","cases":"4,154","iso":"MAR"},{"country":"Mozambique","cases":"126","iso":"MOZ"},{"country":"Myanmar","cases":"172","iso":"Myanmar"},{"country":"Namibia","cases":"61","iso":"NAM"},{"country":"Nepal","cases":"3,318","iso":"NPL"},{"country":"Netherlands","cases":"39,500","iso":"NLD"},{"country":"New Caledonia","cases":["Jan 28, 2022","740"],"iso":"New_Caledonia"},{"country":"New Zealand","cases":"140","iso":"NZL"},{"country":"Nicaragua","cases":"0","iso":"NIC"},{"country":"Niger","cases":"8","iso":"NER"},{"country":"Nigeria","cases":"89","iso":"NGA"},{"country":"North America","cases":"244,672","iso":"North_America"},{"country":"North Macedonia","cases":"1,836","iso":"MKD"},{"country":"Norway","cases":"14,970","iso":"NOR"},{"country":"Oceania","cases":"47,475","iso":"Oceania"},{"country":"Oman","cases":["Jan 27, 2022","2,441"],"iso":"OMN"},{"country":"Pakistan","cases":"7,958","iso":"PAK"},{"country":"Palau","cases":"11","iso":"PLW"},{"country":"Palestine","cases":["Jan 28, 2022","4,548"],"iso":"Palestine"},{"country":"Panama","cases":"7,004","iso":"PAN"},{"country":"Papua New Guinea","cases":["Jan 28, 2022","270"],"iso":"PNG"},{"country":"Paraguay","cases":"5,101","iso":"PRY"},{"country":"Peru","cases":"40,331","iso":"PER"},{"country":"Philippines","cases":"17,305","iso":"PHL"},{"country":"Poland","cases":"51,690","iso":"POL"},{"country":"Portugal","cases":"59,194","iso":"PRT"},{"country":"Qatar","cases":"1,538","iso":"QAT"},{"country":"Romania","cases":"30,168","iso":"ROU"},{"country":"Russia","cases":"112,302","iso":"RUS"},{"country":"Rwanda","cases":"94","iso":"RWA"},{"country":"Saint Helena","cases":"0","iso":"Saint_Helena"},{"country":"Saint Kitts and Nevis","cases":"26","iso":"KNA"},{"country":"Saint Lucia","cases":"381","iso":"LCA"},{"country":"Saint Pierre and Miquelon","cases":"17","iso":"Saint_Pierre_and_Miquelon"},{"country":"Saint Vincent and the Grenadines","cases":"0","iso":"VCT"},{"country":"Samoa","cases":"1","iso":"WSM"},{"country":"San Marino","cases":["Jan 28, 2022","233"],"iso":"SMR"},{"country":"Sao Tome and Principe","cases":"10","iso":"STP"},{"country":"Saudi Arabia","cases":"3,913","iso":"SAU"},{"country":"Senegal","cases":"70","iso":"SEN"},{"country":"Serbia","cases":"15,425","iso":"SRB"},{"country":"Seychelles","cases":["Jan 27, 2022","953"],"iso":"SYC"},{"country":"Sierra Leone","cases":"3","iso":"SLE"},{"country":"Singapore","cases":"5,207","iso":"SGP"},{"country":"Slovakia","cases":"17,808","iso":"SVK"},{"country":"Slovenia","cases":"15,182","iso":"SVN"},{"country":"Solomon Islands","cases":["Jan 28, 2022","143"],"iso":"SLB"},{"country":"Somalia","cases":["Jan 24, 2022","1,066"],"iso":"SOM"},{"country":"South Africa","cases":"3,342","iso":"ZAF"},{"country":"South America","cases":"361,440","iso":"South_America"},{"country":"South Korea","cases":"17,515","iso":"South_Korea"},{"country":"South Sudan","cases":"4","iso":"SSD"},{"country":"Spain","cases":["Jan 28, 2022","118,922"],"iso":"ESP"},{"country":"Sri Lanka","cases":"982","iso":"LKA"},{"country":"Sudan","cases":["Jan 27, 2022","511"],"iso":"SDN"},{"country":"Suriname","cases":"219","iso":"SUR"},{"country":"Sweden","cases":["Jan 28, 2022","55,180"],"iso":"SWE"},{"country":"Switzerland","cases":["Jan 28, 2022","39,771"],"iso":"CHE"},{"country":"Syria","cases":"54","iso":"SYR"},{"country":"Taiwan","cases":"47","iso":"Taiwan"},{"country":"Tajikistan","cases":"0","iso":"TJK"},{"country":"Tanzania","cases":["Jan 25, 2022","527"],"iso":"TZA"},{"country":"Thailand","cases":["Jan 28, 2022","8,618"],"iso":"THA"},{"country":"Timor","cases":"14","iso":"Timor"},{"country":"Togo","cases":"0","iso":"TGO"},{"country":"Tonga","cases":"0","iso":"TON"},{"country":"Trinidad and Tobago","cases":"1,081","iso":"TTO"},{"country":"Tunisia","cases":"16,519","iso":"TUN"},{"country":"Turkey","cases":"94,783","iso":"TUR"},{"country":"Turks and Caicos Islands","cases":"35","iso":"Turks_and_Caicos_Islands"},{"country":"Uganda","cases":"82","iso":"UGA"},{"country":"Ukraine","cases":"38,171","iso":"UKR"},{"country":"United Arab Emirates","cases":"2,355","iso":"ARE"},{"country":"United Kingdom","cases":"72,143","iso":"GBR"},{"country":"United States","cases":"169,002","iso":"United_States"},{"country":"Upper middle income","cases":"711,125","iso":"Upper_middle_income"},{"country":"Uruguay","cases":"9,222","iso":"URY"},{"country":"Uzbekistan","cases":"1,152","iso":"UZB"},{"country":"Vanuatu","cases":"0","iso":"VUT"},{"country":"Vatican","cases":"0","iso":"Vatican"},{"country":"Venezuela","cases":"2,364","iso":"VEN"},{"country":"Vietnam","cases":"15,150","iso":"VNM"},{"country":"Wallis and Futuna","cases":"0","iso":"Wallis_and_Futuna"},{"country":"World","cases":"2.60 million","iso":"World"},{"country":"Yemen","cases":"0","iso":"YEM"},{"country":"Zambia","cases":"303","iso":"ZMB"},{"country":"Zimbabwe","cases":"82","iso":"ZWE"}]}