{"current_hospitalized":[{"country":"Australia","current_hospitalized":"5,021","iso":"AUS"},{"country":"Austria","current_hospitalized":"1,302","iso":"AUT"},{"country":"Belgium","current_hospitalized":"3,694","iso":"BEL"},{"country":"Bulgaria","current_hospitalized":["Jan 23, 2022","5,216"],"iso":"BGR"},{"country":"Canada","current_hospitalized":"10,561","iso":"CAN"},{"country":"Croatia","current_hospitalized":["Jan 9, 2022 ",",874"],"iso":"HRV"},{"country":"Cyprus","current_hospitalized":["Jan 23, 2022","329"],"iso":"CYP"},{"country":"Czechia","current_hospitalized":"1,967","iso":"CZE"},{"country":"Denmark","current_hospitalized":"955","iso":"DNK"},{"country":"Estonia","current_hospitalized":["Jan 23, 2022","320"],"iso":"EST"},{"country":"Finland","current_hospitalized":"675","iso":"FIN"},{"country":"France","current_hospitalized":"30,982","iso":"FRA"},{"country":"Hungary","current_hospitalized":["Jan 23, 2022","2,674"],"iso":"HUN"},{"country":"Iceland","current_hospitalized":["Jan 19, 2022","39"],"iso":"ISL"},{"country":"Ireland","current_hospitalized":["Jan 23, 2022","845"],"iso":"IRL"},{"country":"Israel","current_hospitalized":"2,379","iso":"ISR"},{"country":"Italy","current_hospitalized":"21,498","iso":"ITA"},{"country":"Japan","current_hospitalized":["Jan 26, 2022","17,269"],"iso":"JPN"},{"country":"Latvia","current_hospitalized":["Jan 23, 2022","630"],"iso":"LVA"},{"country":"Lithuania","current_hospitalized":["Jan 23, 2022","1,058"],"iso":"LTU"},{"country":"Luxembourg","current_hospitalized":["Jan 23, 2022","70"],"iso":"LUX"},{"country":"Malaysia","current_hospitalized":"2,002","iso":"MYS"},{"country":"Malta","current_hospitalized":["Jan 21, 2022","99"],"iso":"MLT"},{"country":"Netherlands","current_hospitalized":"898","iso":"NLD"},{"country":"Norway","current_hospitalized":["Jan 23, 2022","227"],"iso":"NOR"},{"country":"Poland","current_hospitalized":["Jan 23, 2022","13,491"],"iso":"POL"},{"country":"Portugal","current_hospitalized":"2,249","iso":"PRT"},{"country":"Serbia","current_hospitalized":"3,301","iso":"SRB"},{"country":"Singapore","current_hospitalized":"601","iso":"SGP"},{"country":"Slovakia","current_hospitalized":["Jan 23, 2022","1,497"],"iso":"SVK"},{"country":"Slovenia","current_hospitalized":["Jan 23, 2022","608"],"iso":"SVN"},{"country":"Spain","current_hospitalized":["Jan 26, 2022","16,449"],"iso":"ESP"},{"country":"Sweden","current_hospitalized":"2,011","iso":"SWE"},{"country":"Switzerland","current_hospitalized":"1,933","iso":"CHE"},{"country":"United Kingdom","current_hospitalized":["Jan 26, 2022","16,510"],"iso":"GBR"},{"country":"United States","current_hospitalized":["Jan 25, 2022","141,591"],"iso":"United_States"}]}