{"people_fully_vaccinated":[{"people_fully_vaccinated":0},{"people_fully_vaccinated":0},{"people_fully_vaccinated":0},{"people_fully_vaccinated":0},{"people_fully_vaccinated":0},{"people_fully_vaccinated":0},{"people_fully_vaccinated":0},{"people_fully_vaccinated":0},{"people_fully_vaccinated":0},{"people_fully_vaccinated":0},{"people_fully_vaccinated":0},{"people_fully_vaccinated":0},{"people_fully_vaccinated":0},{"people_fully_vaccinated":0},{"people_fully_vaccinated":0},{"people_fully_vaccinated":0},{"people_fully_vaccinated":0},{"people_fully_vaccinated":0},{"people_fully_vaccinated":0},{"people_fully_vaccinated":0},{"people_fully_vaccinated":0},{"people_fully_vaccinated":0},{"people_fully_vaccinated":0},{"people_fully_vaccinated":0},{"people_fully_vaccinated":0},{"people_fully_vaccinated":0},{"people_fully_vaccinated":0},{"people_fully_vaccinated":0},{"people_fully_vaccinated":0},{"people_fully_vaccinated":0},{"people_fully_vaccinated":0},{"people_fully_vaccinated":0},{"people_fully_vaccinated":0},{"people_fully_vaccinated":0},{"people_fully_vaccinated":0},{"people_fully_vaccinated":0},{"people_fully_vaccinated":0},{"people_fully_vaccinated":0},{"people_fully_vaccinated":0},{"people_fully_vaccinated":0},{"people_fully_vaccinated":0},{"people_fully_vaccinated":0},{"people_fully_vaccinated":0},{"people_fully_vaccinated":0},{"people_fully_vaccinated":0},{"people_fully_vaccinated":0},{"people_fully_vaccinated":0},{"people_fully_vaccinated":0},{"people_fully_vaccinated":0},{"people_fully_vaccinated":0},{"people_fully_vaccinated":0},{"people_fully_vaccinated":0},{"people_fully_vaccinated":0},{"people_fully_vaccinated":0},{"people_fully_vaccinated":0},{"people_fully_vaccinated":0},{"people_fully_vaccinated":0},{"people_fully_vaccinated":0},{"people_fully_vaccinated":0},{"people_fully_vaccinated":0},{"people_fully_vaccinated":0},{"people_fully_vaccinated":0},{"people_fully_vaccinated":0},{"people_fully_vaccinated":0},{"people_fully_vaccinated":0},{"people_fully_vaccinated":0},{"people_fully_vaccinated":0},{"people_fully_vaccinated":0},{"people_fully_vaccinated":0},{"people_fully_vaccinated":0},{"people_fully_vaccinated":0},{"people_fully_vaccinated":0},{"people_fully_vaccinated":0},{"people_fully_vaccinated":0},{"people_fully_vaccinated":0},{"people_fully_vaccinated":0},{"people_fully_vaccinated":0},{"people_fully_vaccinated":0},{"people_fully_vaccinated":0},{"people_fully_vaccinated":0},{"people_fully_vaccinated":0},{"people_fully_vaccinated":0},{"people_fully_vaccinated":0},{"people_fully_vaccinated":0},{"people_fully_vaccinated":0},{"people_fully_vaccinated":0},{"people_fully_vaccinated":0},{"people_fully_vaccinated":0},{"people_fully_vaccinated":0},{"people_fully_vaccinated":0},{"people_fully_vaccinated":0},{"people_fully_vaccinated":0},{"people_fully_vaccinated":0},{"people_fully_vaccinated":0},{"people_fully_vaccinated":0},{"people_fully_vaccinated":0},{"people_fully_vaccinated":0},{"people_fully_vaccinated":0},{"people_fully_vaccinated":0},{"people_fully_vaccinated":0},{"people_fully_vaccinated":0},{"people_fully_vaccinated":0},{"people_fully_vaccinated":0},{"people_fully_vaccinated":0},{"people_fully_vaccinated":0},{"people_fully_vaccinated":0},{"people_fully_vaccinated":0},{"people_fully_vaccinated":0},{"people_fully_vaccinated":0},{"people_fully_vaccinated":0},{"people_fully_vaccinated":0},{"people_fully_vaccinated":0},{"people_fully_vaccinated":0},{"people_fully_vaccinated":0},{"people_fully_vaccinated":0},{"people_fully_vaccinated":0},{"people_fully_vaccinated":0},{"people_fully_vaccinated":0},{"people_fully_vaccinated":0},{"people_fully_vaccinated":0},{"people_fully_vaccinated":0},{"people_fully_vaccinated":0},{"people_fully_vaccinated":0},{"people_fully_vaccinated":0},{"people_fully_vaccinated":0},{"people_fully_vaccinated":0},{"people_fully_vaccinated":0},{"people_fully_vaccinated":0},{"people_fully_vaccinated":0},{"people_fully_vaccinated":0},{"people_fully_vaccinated":0},{"people_fully_vaccinated":0},{"people_fully_vaccinated":0},{"people_fully_vaccinated":0},{"people_fully_vaccinated":0},{"people_fully_vaccinated":0},{"people_fully_vaccinated":0},{"people_fully_vaccinated":0},{"people_fully_vaccinated":0},{"people_fully_vaccinated":0},{"people_fully_vaccinated":0},{"people_fully_vaccinated":0},{"people_fully_vaccinated":0},{"people_fully_vaccinated":0},{"people_fully_vaccinated":0},{"people_fully_vaccinated":0},{"people_fully_vaccinated":0},{"people_fully_vaccinated":0},{"people_fully_vaccinated":0},{"people_fully_vaccinated":0},{"people_fully_vaccinated":0},{"people_fully_vaccinated":0},{"people_fully_vaccinated":0},{"people_fully_vaccinated":0},{"people_fully_vaccinated":0},{"people_fully_vaccinated":0},{"people_fully_vaccinated":0},{"people_fully_vaccinated":0},{"people_fully_vaccinated":0},{"people_fully_vaccinated":0},{"people_fully_vaccinated":0},{"people_fully_vaccinated":0},{"people_fully_vaccinated":0},{"people_fully_vaccinated":0},{"people_fully_vaccinated":0},{"people_fully_vaccinated":0},{"people_fully_vaccinated":0},{"people_fully_vaccinated":0},{"people_fully_vaccinated":0},{"people_fully_vaccinated":0},{"people_fully_vaccinated":0},{"people_fully_vaccinated":0},{"people_fully_vaccinated":0},{"people_fully_vaccinated":0},{"people_fully_vaccinated":0},{"people_fully_vaccinated":0},{"people_fully_vaccinated":0},{"people_fully_vaccinated":0},{"people_fully_vaccinated":0},{"people_fully_vaccinated":0},{"people_fully_vaccinated":0},{"people_fully_vaccinated":0},{"people_fully_vaccinated":0},{"people_fully_vaccinated":0},{"people_fully_vaccinated":0},{"people_fully_vaccinated":0},{"people_fully_vaccinated":0},{"people_fully_vaccinated":0},{"people_fully_vaccinated":0},{"people_fully_vaccinated":0},{"people_fully_vaccinated":0},{"people_fully_vaccinated":0},{"people_fully_vaccinated":0},{"people_fully_vaccinated":0},{"people_fully_vaccinated":0},{"people_fully_vaccinated":0},{"people_fully_vaccinated":0},{"people_fully_vaccinated":0},{"people_fully_vaccinated":0},{"people_fully_vaccinated":0},{"people_fully_vaccinated":0},{"people_fully_vaccinated":0},{"people_fully_vaccinated":0},{"people_fully_vaccinated":0},{"people_fully_vaccinated":0},{"people_fully_vaccinated":0},{"people_fully_vaccinated":0},{"people_fully_vaccinated":0},{"people_fully_vaccinated":0},{"people_fully_vaccinated":0},{"people_fully_vaccinated":0},{"people_fully_vaccinated":0},{"people_fully_vaccinated":0},{"people_fully_vaccinated":0},{"people_fully_vaccinated":0},{"people_fully_vaccinated":0},{"people_fully_vaccinated":0},{"people_fully_vaccinated":0},{"people_fully_vaccinated":0},{"people_fully_vaccinated":0},{"people_fully_vaccinated":0},{"people_fully_vaccinated":0},{"people_fully_vaccinated":0},{"people_fully_vaccinated":0},{"people_fully_vaccinated":0},{"people_fully_vaccinated":0},{"people_fully_vaccinated":0},{"people_fully_vaccinated":0},{"people_fully_vaccinated":0},{"people_fully_vaccinated":0},{"people_fully_vaccinated":0}],"recent_update":"2022-08-17T23:38:26.406Z"}